{"format":2,"version":"5.0","globals":"8b3bb5296672995f03523513609089b1","files":{"blueprints___init___py":{"hash":"4fbab8abab591cdd413b2371c3cef94a","index":{"nums":[1,57,0,0,0,0,0],"html_filename":"blueprints___init___py.html","relative_filename":"blueprints/__init__.py"}},"blueprints_admin___init___py":{"hash":"ae2bbab2c3e14482732b9973c9950ae7","index":{"nums":[1,58,0,2,0,0,0],"html_filename":"blueprints_admin___init___py.html","relative_filename":"blueprints/admin/__init__.py"}},"blueprints_auth___init___py":{"hash":"23a3cfcc0eb5c6d399f029a48cc34da8","index":{"nums":[1,73,0,2,0,0,0],"html_filename":"blueprints_auth___init___py.html","relative_filename":"blueprints/auth/__init__.py"}},"blueprints_books___init___py":{"hash":"af9d0d0de0ea3b71d198bc63f1499a7d","index":{"nums":[1,0,0,0,0,0,0],"html_filename":"blueprints_books___init___py.html","relative_filename":"blueprints/books/__init__.py"}},"blueprints_books_model_py":{"hash":"df96551c495059375d12ce8610f4d0b1","index":{"nums":[1,33,0,0,0,0,0],"html_filename":"blueprints_books_model_py.html","relative_filename":"blueprints/books/model.py"}},"blueprints_books_resources_py":{"hash":"7625b5c9aeaa1d485fe2ec2535bb26b4","index":{"nums":[1,148,0,2,0,0,0],"html_filename":"blueprints_books_resources_py.html","relative_filename":"blueprints/books/resources.py"}},"blueprints_public___init___py":{"hash":"03c64514409da5efe30af4c9f8a31e1e","index":{"nums":[1,68,0,2,0,0,0],"html_filename":"blueprints_public___init___py.html","relative_filename":"blueprints/public/__init__.py"}},"blueprints_transaction___init___py":{"hash":"af9d0d0de0ea3b71d198bc63f1499a7d","index":{"nums":[1,0,0,0,0,0,0],"html_filename":"blueprints_transaction___init___py.html","relative_filename":"blueprints/transaction/__init__.py"}},"blueprints_transaction_model_py":{"hash":"211cf4229ac5f7a2f8d1d4007240af55","index":{"nums":[1,20,0,0,0,0,0],"html_filename":"blueprints_transaction_model_py.html","relative_filename":"blueprints/transaction/model.py"}},"blueprints_transaction_resources_py":{"hash":"21e6d52cbfc8e99f15c3deeddeb1b207","index":{"nums":[1,90,0,1,0,0,0],"html_filename":"blueprints_transaction_resources_py.html","relative_filename":"blueprints/transaction/resources.py"}},"blueprints_transaction_detail___init___py":{"hash":"af9d0d0de0ea3b71d198bc63f1499a7d","index":{"nums":[1,0,0,0,0,0,0],"html_filename":"blueprints_transaction_detail___init___py.html","relative_filename":"blueprints/transaction_detail/__init__.py"}},"blueprints_transaction_detail_model_py":{"hash":"2ab6c1da339d3b7acd1ffceed59f6db7","index":{"nums":[1,19,0,0,0,0,0],"html_filename":"blueprints_transaction_detail_model_py.html","relative_filename":"blueprints/transaction_detail/model.py"}},"blueprints_users___init___py":{"hash":"af9d0d0de0ea3b71d198bc63f1499a7d","index":{"nums":[1,0,0,0,0,0,0],"html_filename":"blueprints_users___init___py.html","relative_filename":"blueprints/users/__init__.py"}},"blueprints_users_model_py":{"hash":"23b04f037d902e0374a7d674105007cb","index":{"nums":[1,27,0,0,0,0,0],"html_filename":"blueprints_users_model_py.html","relative_filename":"blueprints/users/model.py"}},"blueprints_users_resources_py":{"hash":"1784519e7bc550101a076a4db124c05e","index":{"nums":[1,193,0,7,0,0,0],"html_filename":"blueprints_users_resources_py.html","relative_filename":"blueprints/users/resources.py"}},"blueprints_email___init___py":{"hash":"af9d0d0de0ea3b71d198bc63f1499a7d","index":{"nums":[1,0,0,0,0,0,0],"html_filename":"blueprints_email___init___py.html","relative_filename":"blueprints/email/__init__.py"}},"blueprints_email_resources_py":{"hash":"73242fb1002291eedb068c3de53ff006","index":{"nums":[1,22,0,11,0,0,0],"html_filename":"blueprints_email_resources_py.html","relative_filename":"blueprints/email/resources.py"}}}}